actron_neo_api/__init__.py
actron_neo_api/actron.py
actron_neo_api/const.py
actron_neo_api/exceptions.py
actron_neo_api/oauth.py
actron_neo_api/state.py
actron_neo_api/models/__init__.py
actron_neo_api/models/base.py
actron_neo_api/models/schemas.py
actron_neo_api/models/settings.py
actron_neo_api/models/status.py
actron_neo_api/models/system.py
actron_neo_api/models/zone.py
actron_neo_api-0.4.1.dist-info/licenses/LICENSE
actron_neo_api-0.4.1.dist-info/METADATA
actron_neo_api-0.4.1.dist-info/WHEEL
actron_neo_api-0.4.1.dist-info/top_level.txt
actron_neo_api-0.4.1.dist-info/RECORD
