Metadata-Version: 2.4
Name: actron-neo-api
Version: 0.4.1
Summary: Python API wrapper for the Actron Neo API.
Author-email: Kurt Chrisford <soft.year7030@fastmail.com>
Project-URL: Homepage, https://github.com/kclif9/actronneoapi
Project-URL: Issues, https://github.com/kclif9/actronneoapi/issues
Classifier: Programming Language :: Python :: 3
Classifier: License :: OSI Approved :: MIT License
Classifier: Operating System :: OS Independent
Requires-Python: >=3.8
License-File: LICENSE
Requires-Dist: aiohttp>=3.8.0
Requires-Dist: pydantic>=2.0.0
Provides-Extra: dev
Requires-Dist: mypy>=1.11.0; extra == "dev"
Requires-Dist: pytest>=8.0.0; extra == "dev"
Requires-Dist: pytest-asyncio>=0.24.0; extra == "dev"
Requires-Dist: pytest-cov>=6.0.0; extra == "dev"
Requires-Dist: pre-commit>=3.0.0; extra == "dev"
Requires-Dist: ruff>=0.8.0; extra == "dev"
Dynamic: license-file
